pyppium/__init__.py
pyppium/browserstack.py
pyppium/condition.py
pyppium/driver.py
pyppium/exception.py
pyppium/fetcher.py
pyppium/log.py
pyppium/settings.py
pyppium/utils/__init__.py
pyppium/utils/decorators.py
pyppium/utils/helper.py
pyppium-0.5.1.dist-info/LICENSE
pyppium-0.5.1.dist-info/WHEEL
pyppium-0.5.1.dist-info/METADATA
pyppium-0.5.1.dist-info/RECORD
