Metadata-Version: 2.1
Name: pyppium
Version: 0.5.1
Summary: Pyppium is a wrapper of Appium-Python-Client for cross mobile testing.
Home-page: https://github.com/leomenezessz/pyppium
License: MIT
Keywords: appium,qa,mobile-testing
Author: Leonardo Menezes
Author-email: leonardosmenezes.ssz@gmail.com
Requires-Python: >=3.7,<4.0
Classifier: License :: OSI Approved :: MIT License
Classifier: Programming Language :: Python :: 3
Classifier: Programming Language :: Python :: 3.6
Classifier: Programming Language :: Python :: 3.7
Classifier: Programming Language :: Python :: 3.8
Classifier: Topic :: Software Development :: Libraries
Classifier: Topic :: Software Development :: Quality Assurance
Classifier: Topic :: Software Development :: Testing
Classifier: Topic :: Utilities
Requires-Dist: Appium-Python-Client (==1.0.2)
Requires-Dist: PyYAML (==5.3.1)
Requires-Dist: httpx (==0.14.3)
Requires-Dist: loguru (==0.5.1)
Project-URL: Repository, https://github.com/leomenezessz/pyppium
